westergaard_species
