Metadata-Version: 1.0
Name: westergaard-species
Version: 0.3
Summary: Utilities typeset Westergaard's Species Counterpoint analysis
Home-page: https://github.com/cryptonomicon314/westergaard-species.git
Author: Cryptonomicon
Author-email: cryptonomicon.314@gmail.com
License: MIT
Platform: UNKNOWN
